swift_conductor/__init__.py
swift_conductor/configuration.py
swift_conductor/automation/__init__.py
swift_conductor/automation/worker_host.py
swift_conductor/automation/worker_process.py
swift_conductor/clients/__init__.py
swift_conductor/clients/base_client.py
swift_conductor/clients/event_client.py
swift_conductor/clients/metadata_client.py
swift_conductor/clients/task_client.py
swift_conductor/clients/workflow_client.py
swift_conductor/event_queue/__init__.py
swift_conductor/event_queue/kafka_queue_configuration.py
swift_conductor/event_queue/queue_configuration.py
swift_conductor/event_queue/queue_worker_configuration.py
swift_conductor/exceptions/__init__.py
swift_conductor/exceptions/api_error.py
swift_conductor/exceptions/api_exception_handler.py
swift_conductor/http/__init__.py
swift_conductor/http/api_client.py
swift_conductor/http/rest.py
swift_conductor/http/thread.py
swift_conductor/http/api/__init__.py
swift_conductor/http/api/event_resource_api.py
swift_conductor/http/api/metadata_resource_api.py
swift_conductor/http/api/task_resource_api.py
swift_conductor/http/api/workflow_bulk_resource_api.py
swift_conductor/http/api/workflow_resource_api.py
swift_conductor/http/models/__init__.py
swift_conductor/http/models/action.py
swift_conductor/http/models/bulk_response.py
swift_conductor/http/models/correlation_ids_search_request.py
swift_conductor/http/models/event_handler.py
swift_conductor/http/models/external_storage_location.py
swift_conductor/http/models/health.py
swift_conductor/http/models/health_check_status.py
swift_conductor/http/models/poll_data.py
swift_conductor/http/models/rerun_workflow_request.py
swift_conductor/http/models/response.py
swift_conductor/http/models/scrollable_search_result_workflow_summary.py
swift_conductor/http/models/search_result_task.py
swift_conductor/http/models/search_result_task_summary.py
swift_conductor/http/models/search_result_workflow.py
swift_conductor/http/models/search_result_workflow_summary.py
swift_conductor_client-1.2.0.dist-info/LICENSE.md
swift_conductor_client-1.2.0.dist-info/METADATA
swift_conductor_client-1.2.0.dist-info/WHEEL
swift_conductor_client-1.2.0.dist-info/top_level.txt
swift_conductor_client-1.2.0.dist-info/RECORD
