Metadata-Version: 2.1
Name: swift-conductor-client
Version: 1.2.0
Summary: Swift Conductor Client SDK for Python
Home-page: https://github.com/swift-conductor/conductor-client-python
Author: Swift Software Group
Author-email: hello@swiftsoftwaregroup.com
Classifier: Development Status :: 5 - Production/Stable
Classifier: Intended Audience :: Developers
Classifier: Intended Audience :: System Administrators
Classifier: License :: OSI Approved :: Apache Software License
Classifier: Operating System :: OS Independent
Classifier: Programming Language :: Python :: 3
Classifier: Topic :: Software Development :: Libraries :: Python Modules
Classifier: Topic :: Software Development :: Libraries :: Application Frameworks
Requires-Python: >=3.8
License-File: LICENSE.md
Requires-Dist: certifi >=14.05.14
Requires-Dist: prometheus-client >=0.13.1
Requires-Dist: six >=1.10
Requires-Dist: requests >=2.28.1
Requires-Dist: typing-extensions >=4.2.0
Requires-Dist: astor >=0.8.1
Requires-Dist: shortuuid >=1.0.11
